rtl/async_fifo.sv
// =============================================================================
// Module  : async_fifo
// Author  : Gowtham Kumar Maruthi
// GitHub  : github.com/gowthamaruthi/async-fifo-formal-sv
// Desc    : Parameterized dual-clock asynchronous FIFO with Gray-coded CDC.
//           Combinational full/empty flags. Combinational read port.
//           Simulation checks via always blocks; formal SVA via `ifdef FORMAL.
// =============================================================================

`timescale 1ns / 1ps

module async_fifo #(
  parameter int DEPTH = 16,    // Must be a power of 2, minimum 4
  parameter int WIDTH = 8      // Data width
) (
  // ──── Write clock domain ────────────────────────────────────────────────
  input  logic             wr_clk,
  input  logic             wr_rst_n,   // Active-low async reset
  input  logic             wr_en,
  input  logic [WIDTH-1:0] wr_data,
  output logic             full,

  // ──── Read clock domain ─────────────────────────────────────────────────
  input  logic             rd_clk,
  input  logic             rd_rst_n,   // Active-low async reset
  input  logic             rd_en,
  output logic [WIDTH-1:0] rd_data,
  output logic             empty
);

  localparam int ADDR_W = $clog2(DEPTH);  // address bits
  localparam int PTR_W  = ADDR_W + 1;    // pointer width (extra MSB = wrap bit)

  initial begin
    if (DEPTH < 4 || (DEPTH & (DEPTH - 1)) != 0)
      $fatal(1, "async_fifo: DEPTH must be power-of-2 and >= 4 (got %0d)", DEPTH);
  end

  // ──── Shared memory ─────────────────────────────────────────────────────
  logic [WIDTH-1:0] mem [0:DEPTH-1];

  // ========================================================================
  // Write clock domain
  // ========================================================================

  logic [PTR_W-1:0] wr_bin,     wr_gray;
  logic [PTR_W-1:0] wr_bin_inc;

  assign wr_bin_inc = wr_bin + 1'b1;   // next binary pointer (pre-computed)

  always_ff @(posedge wr_clk or negedge wr_rst_n) begin
    if (!wr_rst_n) begin
      wr_bin  <= '0;
      wr_gray <= '0;
    end else if (wr_en && !full) begin
      wr_bin  <= wr_bin_inc;
      wr_gray <= wr_bin_inc ^ (wr_bin_inc >> 1);   // binary-to-gray
    end
  end

  always_ff @(posedge wr_clk)
    if (wr_en && !full)
      mem[wr_bin[ADDR_W-1:0]] <= wr_data;

  // 2-FF synchronizer: rd_gray ──► write domain
  logic [PTR_W-1:0] rd_gray_q1, rd_gray_sync;
  always_ff @(posedge wr_clk or negedge wr_rst_n) begin
    if (!wr_rst_n) begin
      rd_gray_q1   <= '0;
      rd_gray_sync <= '0;
    end else begin
      rd_gray_q1   <= rd_gray;
      rd_gray_sync <= rd_gray_q1;
    end
  end

  // Full: wr_gray matches rd_gray_sync with top-2 bits inverted
  // (Cummings 2002 dual-MSB method — detects write pointer lapping read by DEPTH)
  assign full = (wr_gray == {~rd_gray_sync[PTR_W-1],
                             ~rd_gray_sync[PTR_W-2],
                              rd_gray_sync[PTR_W-3:0]});

  // ========================================================================
  // Read clock domain
  // ========================================================================

  logic [PTR_W-1:0] rd_bin,     rd_gray;
  logic [PTR_W-1:0] rd_bin_inc;

  assign rd_bin_inc = rd_bin + 1'b1;

  always_ff @(posedge rd_clk or negedge rd_rst_n) begin
    if (!rd_rst_n) begin
      rd_bin  <= '0;
      rd_gray <= '0;
    end else if (rd_en && !empty) begin
      rd_bin  <= rd_bin_inc;
      rd_gray <= rd_bin_inc ^ (rd_bin_inc >> 1);
    end
  end

  // Combinational read port: data valid whenever !empty
  assign rd_data = mem[rd_bin[ADDR_W-1:0]];

  // 2-FF synchronizer: wr_gray ──► read domain
  logic [PTR_W-1:0] wr_gray_q1, wr_gray_sync;
  always_ff @(posedge rd_clk or negedge rd_rst_n) begin
    if (!rd_rst_n) begin
      wr_gray_q1   <= '0;
      wr_gray_sync <= '0;
    end else begin
      wr_gray_q1   <= wr_gray;
      wr_gray_sync <= wr_gray_q1;
    end
  end

  // Empty: rd_gray equals synchronized wr_gray
  assign empty = (rd_gray == wr_gray_sync);

  // ========================================================================
  // Simulation-time violation monitors
  // ========================================================================
  // (Replaced by formal SVA when compiled with `define FORMAL for sby)

`ifndef FORMAL
  always @(posedge wr_clk)
    if (wr_rst_n && wr_en && full)
      $error("[%0t ns] RTL MONITOR: OVERFLOW — wr_en=1 while full=1", $time);

  always @(posedge rd_clk)
    if (rd_rst_n && rd_en && empty)
      $error("[%0t ns] RTL MONITOR: UNDERFLOW — rd_en=1 while empty=1", $time);
`endif

  // ========================================================================
  // Formal SVA assertions (SymbiYosys flow: compile with +define+FORMAL)
  // ========================================================================
`ifdef FORMAL
  // Assume resets are released at some point
  assume property (@(posedge wr_clk) !$isunknown(wr_rst_n));
  assume property (@(posedge rd_clk) !$isunknown(rd_rst_n));

  // No write when full
  assert property (@(posedge wr_clk) disable iff (!wr_rst_n)
    !(wr_en && full));

  // No read when empty
  assert property (@(posedge rd_clk) disable iff (!rd_rst_n)
    !(rd_en && empty));

  // Must start empty after reset
  assert property (@(posedge rd_clk) $rose(rd_rst_n) |-> empty);
`endif

endmodule

tb/tb_async_fifo.sv
// =============================================================================
// Module  : tb_async_fifo
// Author  : Gowtham Kumar Maruthi
// Desc    : Self-checking testbench for async_fifo.
//           Two independent clocks at different frequencies.
//           Scoreboard tracks every write/read for data integrity.
//           Tests: burst, full flag, empty flag, interleaved.
// =============================================================================

`timescale 1ns / 1ps

module tb_async_fifo;

  // ──── Parameters ────────────────────────────────────────────────────────
  localparam int DEPTH   = 16;
  localparam int WIDTH   = 8;
  localparam int ADDR_W  = $clog2(DEPTH);

  localparam real WR_PER = 10.0;   // 100 MHz  write clock
  localparam real RD_PER = 13.0;   //  ~77 MHz  read clock (intentionally different)

  // ──── DUT Signals ───────────────────────────────────────────────────────
  logic             wr_clk, wr_rst_n, wr_en;
  logic [WIDTH-1:0] wr_data;
  logic             full;

  logic             rd_clk, rd_rst_n, rd_en;
  logic [WIDTH-1:0] rd_data;
  logic             empty;

  // ──── DUT ───────────────────────────────────────────────────────────────
  async_fifo #(.DEPTH(DEPTH), .WIDTH(WIDTH)) dut (.*);

  // ──── Clock Generation ──────────────────────────────────────────────────
  initial wr_clk = 1'b0;
  always  #(WR_PER/2) wr_clk = ~wr_clk;

  initial rd_clk = 1'b0;
  always  #(RD_PER/2) rd_clk = ~rd_clk;

  // ──── VCD Dump (for GTKWave) ────────────────────────────────────────────
  initial begin
    $dumpfile("dump.vcd");
    $dumpvars(0, tb_async_fifo);
  end

  // ──── Scoreboard ────────────────────────────────────────────────────────
  int pass_cnt = 0;
  int fail_cnt = 0;
  logic [WIDTH-1:0] exp_q [$];   // expected-data queue (write pushes, read pops)

  // Runtime monitors: catch assertion violations from RTL
  always @(posedge wr_clk)
    if (wr_rst_n && wr_en && full) begin
      $error("[TB MONITOR] OVERFLOW detected at %0t ns!", $time);
      fail_cnt++;
    end

  always @(posedge rd_clk)
    if (rd_rst_n && rd_en && empty) begin
      $error("[TB MONITOR] UNDERFLOW detected at %0t ns!", $time);
      fail_cnt++;
    end

  // ──── Tasks ─────────────────────────────────────────────────────────────

  // Reset both domains
  task automatic apply_reset();
    wr_rst_n = 1'b0;  rd_rst_n = 1'b0;
    wr_en    = 1'b0;  rd_en    = 1'b0;
    wr_data  = '0;
    exp_q    = {};
    repeat (6) @(posedge wr_clk);
    repeat (6) @(posedge rd_clk);
    @(negedge wr_clk); wr_rst_n = 1'b1;
    @(negedge rd_clk); rd_rst_n = 1'b1;
    repeat (2) @(posedge wr_clk);
    $display("[RESET] Released — empty=%0b full=%0b", empty, full);
  endtask

  // Write one item (no-op if full)
  task automatic do_write(input logic [WIDTH-1:0] data);
    @(negedge wr_clk);
    if (full) begin
      $display("[WR] SKIP 0x%02h — FIFO full", data);
    end else begin
      wr_en   = 1'b1;
      wr_data = data;
      exp_q.push_back(data);            // record for scoreboard
      @(posedge wr_clk); #1;
      wr_en = 1'b0;
    end
  endtask

  // Read one item and compare against expected (no-op if empty)
  task automatic do_read();
    logic [WIDTH-1:0] got;
    logic [WIDTH-1:0] expected;
    @(negedge rd_clk);
    if (empty) begin
      $display("[RD] SKIP — FIFO empty");
    end else begin
      got      = rd_data;             // comb output valid NOW (before rd_en)
      expected = exp_q.pop_front();
      rd_en = 1'b1;
      @(posedge rd_clk); #1;   // pointer advances
      rd_en = 1'b0;
      // Scoreboard compare
      if (got === expected) begin
        pass_cnt++;
        $display("[RD] PASS  got=0x%02h  exp=0x%02h", got, expected);
      end else begin
        fail_cnt++;
        $display("[RD] FAIL  got=0x%02h  exp=0x%02h  *** MISMATCH ***", got, expected);
      end
    end
  endtask

  // ──── Test Sequence ─────────────────────────────────────────────────────
  initial begin
    $display("\n============================================================");
    $display("  ASYNC FIFO — SELF-CHECKING TESTBENCH");
    $display("  DEPTH=%0d  WIDTH=%0d  WR=%.0f MHz  RD=%.0f MHz",
             DEPTH, WIDTH, 1000.0/WR_PER, 1000.0/RD_PER);
    $display("============================================================\n");

    apply_reset();

    // ── TEST 1: Burst write then burst read ────────────────────────────
    $display("── TEST 1: Write 8 items, then read 8 items ──────────────");
    for (int i = 0; i < 8; i++) do_write(8'hA0 + i[7:0]);
    // Allow a few wr_clk → rd_clk sync cycles before reading
    repeat(4) @(posedge rd_clk);
    for (int i = 0; i < 8; i++) do_read();

    // ── TEST 2: Fill FIFO to full ──────────────────────────────────────
    $display("\n── TEST 2: Fill FIFO → verify full flag ──────────────────");
    // Drain first
    repeat(4) @(posedge rd_clk);
    while (!empty) do_read();
    exp_q = {};
    repeat(6) @(posedge wr_clk);

    for (int i = 0; i < DEPTH; i++) do_write(8'h10 + i[7:0]);
    repeat(6) @(posedge wr_clk);   // flags settle after CDC sync

    if (full) begin
      pass_cnt++;
      $display("[TEST 2] PASS: full=1 correctly after %0d writes", DEPTH);
    end else begin
      fail_cnt++;
      $display("[TEST 2] FAIL: full not asserted *** ERROR ***");
    end

    // ── TEST 3: Drain FIFO to empty ────────────────────────────────────
    $display("\n── TEST 3: Drain FIFO → verify empty flag ────────────────");
    repeat(4) @(posedge rd_clk);
    for (int i = 0; i < DEPTH; i++) do_read();
    exp_q = {};
    repeat(6) @(posedge rd_clk);   // empty flag settles

    if (empty) begin
      pass_cnt++;
      $display("[TEST 3] PASS: empty=1 correctly after draining %0d items", DEPTH);
    end else begin
      fail_cnt++;
      $display("[TEST 3] FAIL: empty not asserted *** ERROR ***");
    end

    // ── TEST 4: Interleaved write/read (different clock rates) ─────────
    $display("\n── TEST 4: Interleaved writes/reads (async clocks) ───────");
    begin : test4
      integer wr_total;
      integer rd_total;
      reg [WIDTH-1:0] d;
      wr_total = 0; rd_total = 0;

      repeat(4) @(posedge wr_clk);

      for (int i = 0; i < 40; i++) begin
        // Write side: write every 2–3 wr_clk cycles
        repeat($urandom_range(2, 3)) @(posedge wr_clk);
        if (!full) begin
          d = $urandom_range(0, 255);
          do_write(d);
          wr_total++;
        end
        // Read side: read every 3–5 rd_clk cycles
        repeat($urandom_range(3, 5)) @(posedge rd_clk);
        if (!empty) begin
          do_read();
          rd_total++;
        end
      end

      // Drain anything remaining
      repeat(6) @(posedge rd_clk);
      while (!empty) do_read();
      exp_q = {};

      $display("[TEST 4] Wrote %0d items, read %0d items", wr_total, rd_total);
    end

    // ── Final Report ─────────────────────────────────────────────────────
    repeat(4) @(posedge wr_clk);
    $display("\n============================================================");
    $display("  RESULTS  |  PASS: %0d  |  FAIL: %0d", pass_cnt, fail_cnt);
    if (fail_cnt == 0)
      $display("  STATUS   :  ALL TESTS PASSED ✓");
    else
      $display("  STATUS   :  %0d FAILURE(S) DETECTED ✗", fail_cnt);
    $display("============================================================\n");

    $finish;
  end

  // ── Watchdog ─────────────────────────────────────────────────────────────
  initial begin
    #500_000;
    $display("[TIMEOUT] Simulation exceeded limit — check for deadlock");
    $finish;
  end

endmodule

sim/dump.vcd
$date
	Mon Jun 15 13:41:08 2026
$end
$version
	Icarus Verilog
$end
$timescale
	1ps
$end
$scope module tb_async_fifo $end
$var wire 8 ! rd_data [7:0] $end
$var wire 1 " full $end
$var wire 1 # empty $end
$var parameter 32 $ ADDR_W $end
$var parameter 32 % DEPTH $end
$var real 1 & RD_PER $end
$var parameter 32 ' WIDTH $end
$var real 1 ( WR_PER $end
$var reg 1 ) rd_clk $end
$var reg 1 * rd_en $end
$var reg 1 + rd_rst_n $end
$var reg 1 , wr_clk $end
$var reg 8 - wr_data [7:0] $end
$var reg 1 . wr_en $end
$var reg 1 / wr_rst_n $end
$var integer 32 0 fail_cnt [31:0] $end
$var integer 32 1 pass_cnt [31:0] $end
$scope module dut $end
$var wire 1 ) rd_clk $end
$var wire 8 2 rd_data [7:0] $end
$var wire 1 * rd_en $end
$var wire 1 + rd_rst_n $end
$var wire 1 , wr_clk $end
$var wire 8 3 wr_data [7:0] $end
$var wire 1 . wr_en $end
$var wire 1 / wr_rst_n $end
$var wire 5 4 wr_bin_inc [4:0] $end
$var wire 5 5 rd_bin_inc [4:0] $end
$var wire 1 " full $end
$var wire 1 # empty $end
$var parameter 32 6 ADDR_W $end
$var parameter 32 7 DEPTH $end
$var parameter 32 8 PTR_W $end
$var parameter 32 9 WIDTH $end
$var reg 5 : rd_bin [4:0] $end
$var reg 5 ; rd_gray [4:0] $end
$var reg 5 < rd_gray_q1 [4:0] $end
$var reg 5 = rd_gray_sync [4:0] $end
$var reg 5 > wr_bin [4:0] $end
$var reg 5 ? wr_gray [4:0] $end
$var reg 5 @ wr_gray_q1 [4:0] $end
$var reg 5 A wr_gray_sync [4:0] $end
$upscope $end
$scope begin $ivl_for_loop0 $end
$var integer 32 B i [31:0] $end
$upscope $end
$scope begin $ivl_for_loop1 $end
$var integer 32 C i [31:0] $end
$upscope $end
$scope begin $ivl_for_loop2 $end
$var integer 32 D i [31:0] $end
$upscope $end
$scope begin $ivl_for_loop3 $end
$var integer 32 E i [31:0] $end
$upscope $end
$scope begin test4 $end
$var reg 8 F d [7:0] $end
$var integer 32 G rd_total [31:0] $end
$var integer 32 H wr_total [31:0] $end
$scope begin $ivl_for_loop4 $end
$var integer 32 I i [31:0] $end
$upscope $end
$upscope $end
$scope task apply_reset $end
$upscope $end
$scope task do_read $end
$upscope $end
$scope task do_write $end
$upscope $end
$upscope $end
$enddefinitions $end
$comment Show the parameter values. $end
$dumpall
b1000 9
b101 8
b10000 7
b100 6
r10 (
b1000 '
r13 &
b10000 %
b100 $
$end
#0
$dumpvars
b0 I
bx H
bx G
bx F
b0 E
b0 D
b0 C
b0 B
b0 A
b0 @
b0 ?
b0 >
b0 =
b0 <
b0 ;
b0 :
b1 5
b1 4
b0 3
bx 2
b0 1
b0 0
0/
0.
b0 -
0,
0+
0*
0)
1#
0"
bx !
$end
#5000
1,
#6500
1)
#10000
0,
#13000
0)
#15000
1,
#19500
1)
#20000
0,
#25000
1,
#26000
0)
#30000
0,
#32500
1)
#35000
1,
#39000
0)
#40000
0,
#45000
1,
#45500
1)
#50000
0,
#52000
0)
#55000
1,
#58500
1)
#60000
0,
#65000
1,
0)
#70000
0,
#71500
1)
#75000
1,
#78000
0)
#80000
0,
#84500
1)
#85000
1,
#90000
0,
#91000
0)
#95000
1,
#97500
1)
#100000
0,
#104000
0)
#105000
1,
#110000
0,
#110500
1)
#115000
1,
#117000
0)
#120000
0,
#123500
1)
#125000
1,
#130000
1/
0,
0)
#135000
1,
#136500
1)
#140000
0,
#143000
1+
0)
#145000
1,
#149500
1)
#150000
0,
#155000
1,
#156000
0)
#160000
b10100000 -
b10100000 3
1.
0,
#162500
1)
#165000
b10100000 !
b10100000 2
b1 ?
b10 4
b1 >
1,
#166000
b1 B
0.
#169000
0)
#170000
b10100001 -
b10100001 3
1.
0,
#175000
b11 ?
b11 4
b10 >
1,
#175500
b11 @
1)
#176000
b10 B
0.
#180000
b10100010 -
b10100010 3
1.
0,
#182000
0)
#185000
b10 ?
b100 4
b11 >
1,
#186000
b11 B
0.
#188500
0#
b11 A
b10 @
1)
#190000
b10100011 -
b10100011 3
1.
0,
#195000
b110 ?
b101 4
b100 >
1,
0)
#196000
b100 B
0.
#200000
b10100100 -
b10100100 3
1.
0,
#201500
b10 A
b110 @
1)
#205000
b111 ?
b110 4
b101 >
1,
#206000
b101 B
0.
#208000
0)
#210000
b10100101 -
b10100101 3
1.
0,
#214500
b110 A
b111 @
1)
#215000
b101 ?
b111 4
b110 >
1,
#216000
b110 B
0.
#220000
b10100110 -
b10100110 3
1.
0,
#221000
0)
#225000
b100 ?
b1000 4
b111 >
1,
#226000
b111 B
0.
#227500
b111 A
b100 @
1)
#230000
b10100111 -
b10100111 3
1.
0,
#234000
0)
#235000
b1100 ?
b1001 4
b1000 >
1,
#236000
b1000 B
0.
#240000
0,
#240500
b100 A
b1100 @
1)
#245000
1,
#247000
0)
#250000
0,
#253500
b1100 A
1)
#255000
1,
#260000
0,
0)
#265000
1,
#266500
1)
#270000
0,
#273000
0)
#275000
1,
#279500
1)
#280000
0,
#285000
1,
#286000
1*
0)
#290000
0,
#292500
b10100001 !
b10100001 2
b1 ;
b10 5
b1 :
1)
#293500
b1 C
b1 1
0*
#295000
b1 <
1,
#299000
1*
0)
#300000
0,
#305000
b1 =
1,
#305500
b10100010 !
b10100010 2
b11 ;
b11 5
b10 :
1)
#306500
b10 C
b10 1
0*
#310000
0,
#312000
1*
0)
#315000
b11 <
1,
#318500
b10100011 !
b10100011 2
b10 ;
b100 5
b11 :
1)
#319500
b11 C
b11 1
0*
#320000
0,
#325000
b11 =
b10 <
1*
1,
0)
#330000
0,
#331500
b10100100 !
b10100100 2
b110 ;
b101 5
b100 :
1)
#332500
b100 C
b100 1
0*
#335000
b10 =
b110 <
1,
#338000
1*
0)
#340000
0,
#344500
b10100101 !
b10100101 2
b111 ;
b110 5
b101 :
1)
#345000
b110 =
b111 <
1,
#345500
b101 C
b101 1
0*
#350000
0,
#351000
1*
0)
#355000
b111 =
1,
#357500
b10100110 !
b10100110 2
b101 ;
b111 5
b110 :
1)
#358500
b110 C
b110 1
0*
#360000
0,
#364000
1*
0)
#365000
b101 <
1,
#370000
0,
#370500
b10100111 !
b10100111 2
b100 ;
b1000 5
b111 :
1)
#371500
b111 C
b111 1
0*
#375000
b101 =
b100 <
1,
#377000
1*
0)
#380000
0,
#383500
bx !
bx 2
1#
b1100 ;
b1001 5
b1000 :
1)
#384500
b1000 C
b1000 1
0*
#385000
b100 =
b1100 <
1,
#390000
0,
0)
#395000
b1100 =
1,
#396500
1)
#400000
0,
#403000
0)
#405000
1,
#409500
1)
#410000
0,
#415000
1,
#416000
0)
#420000
0,
#422500
1)
#425000
1,
#429000
0)
#430000
0,
#435000
1,
#435500
1)
#440000
0,
#442000
0)
#445000
1,
#448500
1)
#450000
0,
#455000
1,
0)
#460000
0,
#461500
1)
#465000
1,
#468000
0)
#470000
0,
#474500
1)
#475000
1,
#480000
0,
#481000
0)
#485000
1,
#487500
1)
#490000
0,
#494000
0)
#495000
1,
#500000
b10000 -
b10000 3
1.
0,
#500500
1)
#505000
b10000 !
b10000 2
b1101 ?
b1010 4
b1001 >
1,
#506000
b1 D
0.
#507000
0)
#510000
b10001 -
b10001 3
1.
0,
#513500
b1101 @
1)
#515000
b1111 ?
b1011 4
b1010 >
1,
#516000
b10 D
0.
#520000
b10010 -
b10010 3
1.
0,
0)
#525000
b1110 ?
b1100 4
b1011 >
1,
#526000
b11 D
0.
#526500
0#
b1101 A
b1110 @
1)
#530000
b10011 -
b10011 3
1.
0,
#533000
0)
#535000
b1010 ?
b1101 4
b1100 >
1,
#536000
b100 D
0.
#539500
b1110 A
b1010 @
1)
#540000
b10100 -
b10100 3
1.
0,
#545000
b1011 ?
b1110 4
b1101 >
1,
#546000
b101 D
0.
0)
#550000
b10101 -
b10101 3
1.
0,
#552500
b1010 A
b1011 @
1)
#555000
b1001 ?
b1111 4
b1110 >
1,
#556000
b110 D
0.
#559000
0)
#560000
b10110 -
b10110 3
1.
0,
#565000
b1000 ?
b10000 4
b1111 >
1,
#565500
b1011 A
b1000 @
1)
#566000
b111 D
0.
#570000
b10111 -
b10111 3
1.
0,
#572000
0)
#575000
b11000 ?
b10001 4
b10000 >
1,
#576000
b1000 D
0.
#578500
b1000 A
b11000 @
1)
#580000
b11000 -
b11000 3
1.
0,
#585000
b11001 ?
b10010 4
b10001 >
1,
0)
#586000
b1001 D
0.
#590000
b11001 -
b11001 3
1.
0,
#591500
b11000 A
b11001 @
1)
#595000
b11011 ?
b10011 4
b10010 >
1,
#596000
b1010 D
0.
#598000
0)
#600000
b11010 -
b11010 3
1.
0,
#604500
b11001 A
b11011 @
1)
#605000
b11010 ?
b10100 4
b10011 >
1,
#606000
b1011 D
0.
#610000
b11011 -
b11011 3
1.
0,
#611000
0)
#615000
b11110 ?
b10101 4
b10100 >
1,
#616000
b1100 D
0.
#617500
b11011 A
b11110 @
1)
#620000
b11100 -
b11100 3
1.
0,
#624000
0)
#625000
b11111 ?
b10110 4
b10101 >
1,
#626000
b1101 D
0.
#630000
b11101 -
b11101 3
1.
0,
#630500
b11110 A
b11111 @
1)
#635000
b11101 ?
b10111 4
b10110 >
1,
#636000
b1110 D
0.
#637000
0)
#640000
b11110 -
b11110 3
1.
0,
#643500
b11111 A
b11101 @
1)
#645000
b11100 ?
b11000 4
b10111 >
1,
#646000
b1111 D
0.
#650000
b11111 -
b11111 3
1.
0,
0)
#655000
1"
b10100 ?
b11001 4
b11000 >
1,
#656000
b10000 D
0.
#656500
b11101 A
b10100 @
1)
#660000
0,
#663000
0)
#665000
1,
#669500
b10100 A
1)
#670000
0,
#675000
1,
#676000
0)
#680000
0,
#682500
1)
#685000
1,
#689000
0)
#690000
0,
#695000
1,
#695500
1)
#700000
0,
#702000
0)
#705000
1,
#708500
1)
#710000
0,
#715000
b1001 1
1,
0)
#720000
0,
#721500
1)
#725000
1,
#728000
0)
#730000
0,
#734500
1)
#735000
1,
#740000
0,
#741000
0)
#745000
1,
#747500
1)
#750000
0,
#754000
0)
#755000
1,
#760000
0,
#760500
1)
#765000
1,
#767000
1*
0)
#770000
0,
#773500
b10001 !
b10001 2
b1101 ;
b1010 5
b1001 :
1)
#774500
b1 E
b1010 1
0*
#775000
b1101 <
1,
#780000
1*
0,
0)
#785000
0"
b1101 =
1,
#786500
b10010 !
b10010 2
b1111 ;
b1011 5
b1010 :
1)
#787500
b10 E
b1011 1
0*
#790000
0,
#793000
1*
0)
#795000
b1111 <
1,
#799500
b10011 !
b10011 2
b1110 ;
b1100 5
b1011 :
1)
#800000
0,
#800500
b11 E
b1100 1
0*
#805000
b1111 =
b1110 <
1,
#806000
1*
0)
#810000
0,
#812500
b10100 !
b10100 2
b1010 ;
b1101 5
b1100 :
1)
#813500
b100 E
b1101 1
0*
#815000
b1110 =
b1010 <
1,
#819000
1*
0)
#820000
0,
#825000
b1010 =
1,
#825500
b10101 !
b10101 2
b1011 ;
b1110 5
b1101 :
1)
#826500
b101 E
b1110 1
0*
#830000
0,
#832000
1*
0)
#835000
b1011 <
1,
#838500
b10110 !
b10110 2
b1001 ;
b1111 5
b1110 :
1)
#839500
b110 E
b1111 1
0*
#840000
0,
#845000
b1011 =
b1001 <
1*
1,
0)
#850000
0,
#851500
b10111 !
b10111 2
b1000 ;
b10000 5
b1111 :
1)
#852500
b111 E
b10000 1
0*
#855000
b1001 =
b1000 <
1,
#858000
1*
0)
#860000
0,
#864500
b11000 !
b11000 2
b11000 ;
b10001 5
b10000 :
1)
#865000
b1000 =
b11000 <
1,
#865500
b1000 E
b10001 1
0*
#870000
0,
#871000
1*
0)
#875000
b11000 =
1,
#877500
b11001 !
b11001 2
b11001 ;
b10010 5
b10001 :
1)
#878500
b1001 E
b10010 1
0*
#880000
0,
#884000
1*
0)
#885000
b11001 <
1,
#890000
0,
#890500
b11010 !
b11010 2
b11011 ;
b10011 5
b10010 :
1)
#891500
b1010 E
b10011 1
0*
#895000
b11001 =
b11011 <
1,
#897000
1*
0)
#900000
0,
#903500
b11011 !
b11011 2
b11010 ;
b10100 5
b10011 :
1)
#904500
b1011 E
b10100 1
0*
#905000
b11011 =
b11010 <
1,
#910000
1*
0,
0)
#915000
b11010 =
1,
#916500
b11100 !
b11100 2
b11110 ;
b10101 5
b10100 :
1)
#917500
b1100 E
b10101 1
0*
#920000
0,
#923000
1*
0)
#925000
b11110 <
1,
#929500
b11101 !
b11101 2
b11111 ;
b10110 5
b10101 :
1)
#930000
0,
#930500
b1101 E
b10110 1
0*
#935000
b11110 =
b11111 <
1,
#936000
1*
0)
#940000
0,
#942500
b11110 !
b11110 2
b11101 ;
b10111 5
b10110 :
1)
#943500
b1110 E
b10111 1
0*
#945000
b11111 =
b11101 <
1,
#949000
1*
0)
#950000
0,
#955000
b11101 =
1,
#955500
b11111 !
b11111 2
b11100 ;
b11000 5
b10111 :
1)
#956500
b1111 E
b11000 1
0*
#960000
0,
#962000
1*
0)
#965000
b11100 <
1,
#968500
b10000 !
b10000 2
1#
b10100 ;
b11001 5
b11000 :
1)
#969500
b10000 E
b11001 1
0*
#970000
0,
#975000
b11100 =
b10100 <
1,
0)
#980000
0,
#981500
1)
#985000
b10100 =
1,
#988000
0)
#990000
0,
#994500
1)
#995000
1,
#1000000
0,
#1001000
0)
#1005000
1,
#1007500
1)
#1010000
0,
#1014000
0)
#1015000
1,
#1020000
0,
#1020500
1)
#1025000
1,
#1027000
0)
#1030000
0,
#1033500
1)
#1035000
1,
#1040000
0,
0)
#1045000
1,
#1046500
b0 G
b0 H
b11010 1
1)
#1050000
0,
#1053000
0)
#1055000
1,
#1059500
1)
#1060000
0,
#1065000
1,
#1066000
0)
#1070000
0,
#1072500
1)
#1075000
1,
#1079000
0)
#1080000
0,
#1085000
1,
#1085500
1)
#1090000
0,
#1092000
0)
#1095000
1,
#1098500
1)
#1100000
0,
#1105000
1,
0)
#1110000
0,
#1111500
1)
#1115000
b1000000 F
1,
#1118000
0)
#1120000
b1000000 -
b1000000 3
1.
0,
#1124500
1)
#1125000
b1000000 !
b1000000 2
b10101 ?
b11010 4
b11001 >
1,
#1126000
b1 H
0.
#1130000
0,
#1131000
0)
#1135000
1,
#1137500
b10101 @
1)
#1140000
0,
#1144000
0)
#1145000
1,
#1150000
0,
#1150500
0#
b10101 A
1)
#1155000
1,
#1157000
0)
#1160000
0,
#1163500
1)
#1165000
1,
#1170000
1*
0,
0)
#1175000
1,
#1176500
b10001 !
b10001 2
1#
b10101 ;
b11010 5
b11001 :
1)
#1177500
b1 I
b1 G
b11011 1
0*
#1180000
0,
#1183000
0)
#1185000
b10101 <
1,
#1189500
1)
#1190000
0,
#1195000
b10101 =
b10000110 F
1,
#1196000
0)
#1200000
b10000110 -
b10000110 3
1.
0,
#1202500
1)
#1205000
b10000110 !
b10000110 2
b10111 ?
b11011 4
b11010 >
1,
#1206000
b10 H
0.
#1209000
0)
#1210000
0,
#1215000
1,
#1215500
b10111 @
1)
#1220000
0,
#1222000
0)
#1225000
1,
#1228500
0#
b10111 A
1)
#1230000
0,
#1235000
1,
0)
#1240000
0,
#1241500
1)
#1245000
1,
#1248000
0)
#1250000
0,
#1254500
1)
#1255000
1,
#1260000
0,
#1261000
0)
#1265000
1,
#1267500
1)
#1270000
0,
#1274000
1*
0)
#1275000
1,
#1280000
0,
#1280500
b10010 !
b10010 2
1#
b10111 ;
b11011 5
b11010 :
1)
#1281500
b10 I
b10 G
b11100 1
0*
#1285000
b10111 <
1,
#1287000
0)
#1290000
0,
#1293500
1)
#1295000
b10111 =
b1001 F
1,
#1300000
b1001 -
b1001 3
1.
0,
0)
#1305000
b1001 !
b1001 2
b10110 ?
b11100 4
b11011 >
1,
#1306000
b11 H
0.
#1306500
b10110 @
1)
#1310000
0,
#1313000
0)
#1315000
1,
#1319500
0#
b10110 A
1)
#1320000
0,
#1325000
1,
#1326000
0)
#1330000
0,
#1332500
1)
#1335000
1,
#1339000
0)
#1340000
0,
#1345000
1,
#1345500
1)
#1350000
0,
#1352000
1*
0)
#1355000
1,
#1358500
b10011 !
b10011 2
1#
b10110 ;
b11100 5
b11011 :
1)
#1359500
b11 I
b11 G
b11101 1
0*
#1360000
0,
#1365000
b10110 <
1,
0)
#1370000
0,
#1371500
1)
#1375000
b10110 =
1,
#1378000
0)
#1380000
0,
#1384500
1)
#1385000
b10111011 F
1,
#1390000
b10111011 -
b10111011 3
1.
0,
#1391000
0)
#1395000
b10111011 !
b10111011 2
b10010 ?
b11101 4
b11100 >
1,
#1396000
b100 H
0.
#1397500
b10010 @
1)
#1400000
0,
#1404000
0)
#1405000
1,
#1410000
0,
#1410500
0#
b10010 A
1)
#1415000
1,
#1417000
0)
#1420000
0,
#1423500
1)
#1425000
1,
#1430000
0,
0)
#1435000
1,
#1436500
1)
#1440000
0,
#1443000
1*
0)
#1445000
1,
#1449500
b10100 !
b10100 2
1#
b10010 ;
b11101 5
b11100 :
1)
#1450000
0,
#1450500
b100 I
b100 G
b11110 1
0*
#1455000
b10010 <
1,
#1456000
0)
#1460000
0,
#1462500
1)
#1465000
b10010 =
1,
#1469000
0)
#1470000
0,
#1475000
b11000110 F
1,
#1475500
1)
#1480000
b11000110 -
b11000110 3
1.
0,
#1482000
0)
#1485000
b11000110 !
b11000110 2
b10011 ?
b11110 4
b11101 >
1,
#1486000
b101 H
0.
#1488500
b10011 @
1)
#1490000
0,
#1495000
1,
0)
#1500000
0,
#1501500
0#
b10011 A
1)
#1505000
1,
#1508000
0)
#1510000
0,
#1514500
1)
#1515000
1,
#1520000
0,
#1521000
0)
#1525000
1,
#1527500
1)
#1530000
0,
#1534000
0)
#1535000
1,
#1540000
0,
#1540500
1)
#1545000
1,
#1547000
1*
0)
#1550000
0,
#1553500
b10101 !
b10101 2
1#
b10011 ;
b11110 5
b11101 :
1)
#1554500
b101 I
b101 G
b11111 1
0*
#1555000
b10011 <
1,
#1560000
0,
0)
#1565000
b10011 =
b1100010 F
1,
#1566500
1)
#1570000
b1100010 -
b1100010 3
1.
0,
#1573000
0)
